CHANGELOG.txt
LICENCE.txt
MANIFEST.in
README.txt
cape.py
setup.py
NameMC/__init__.py
NameMC/loginms.py
NameMC/test.py
NameMC/loginms/login.py
getcapes/__init__.py
getcapes/list.txt
getcapes/names.txt
getcapes/test.py
getcapes/test.txt
loginms/login.py
mccapes.egg-info/PKG-INFO
mccapes.egg-info/SOURCES.txt
mccapes.egg-info/dependency_links.txt
mccapes.egg-info/requires.txt
mccapes.egg-info/top_level.txt
mycapes/__init__.py
mycapes/loginms.py
mycapes/loginms/login.py
mynames/__init__.py
mynames/loginms.py
mynames/loginms/login.py