Metadata-Version: 1.1
Name: mccapes
Version: 0.2.0
Summary: simple minecraft cape viewer! view other players cape
Home-page: UNKNOWN
Author: Overnice.exe
Author-email: silkepilon2009@gmail.com
License: MIT
Platform: UNKNOWN
Classifier: Development Status :: 5 - Production/Stable
Classifier: Operating System :: OS Independent
Classifier: License :: OSI Approved :: MIT License
Classifier: Programming Language :: Python :: 3
